txt2mrs/__init__.py
txt2mrs/__main__.py
txt2mrs/py.typed
txt2mrs/txt2mrs.py
txt2mrs-0.0.7.dist-info/METADATA
txt2mrs-0.0.7.dist-info/WHEEL
txt2mrs-0.0.7.dist-info/entry_points.txt
txt2mrs-0.0.7.dist-info/RECORD
